all_against_all/LICENSE
all_against_all/README.MD
all_against_all/__init__.py
all_against_all/requirements.txt
all_against_all/thirdparty.json
all_against_all-0.10.dist-info/LICENSE.rst
all_against_all-0.10.dist-info/METADATA
all_against_all-0.10.dist-info/WHEEL
all_against_all-0.10.dist-info/top_level.txt
all_against_all-0.10.dist-info/RECORD
